calculation_test/__init__.py
calculation_test/area.py
calculation_test/distance.py
calculation_test/exif_calc_heading.py
calculation_test/img_transformer.py
calculation_test/increment_version.py
calculation_test/intersection.py
calculation_test/iterator.py
calculation_test/pip_deploy.py
calculation_test/pixel.py
calculation_test/units.py
calculation_test/util.py
calculation_test-0.1.1.dist-info/WHEEL
calculation_test-0.1.1.dist-info/METADATA
calculation_test-0.1.1.dist-info/RECORD
