Metadata-Version: 2.1
Name: calculation-test
Version: 0.1.1
Summary: mapilio calculation
Author: Kadir Coşar
Author-email: kadircosarnew@gmail.com
Requires-Python: >=3.6,<4.0
Classifier: Programming Language :: Python :: 3
Classifier: Programming Language :: Python :: 3.10
Classifier: Programming Language :: Python :: 3.6
Classifier: Programming Language :: Python :: 3.7
Classifier: Programming Language :: Python :: 3.8
Classifier: Programming Language :: Python :: 3.9
Requires-Dist: ExifRead (>=2.3.2,<3.0.0)
Requires-Dist: addict (==2.4.0)
Requires-Dist: geographiclib (==1.50)
Requires-Dist: helper-mapilio (>=1.1.31,<2.0.0)
Requires-Dist: matplotlib (>=3.5.2,<4.0.0)
Requires-Dist: numpy (>=1.23.1,<2.0.0)
Requires-Dist: opencv-python (>=4.5.1.48,<5.0.0.0)
Requires-Dist: pandas
Requires-Dist: pytz (>=2021.1,<2022.0)
Requires-Dist: requests (>=2.25.1,<3.0.0)
Requires-Dist: scipy (>=1.8.1,<2.0.0)
Requires-Dist: solve (>=0.0.0,<0.0.1)
Requires-Dist: trianglesolver (>=1.2,<2.0)
